augment/__init__.py
augment/geometric.py
augment/kernel_based.py
augment/photometric.py
augment_auto-0.1.0.dist-info/LICENSE
augment_auto-0.1.0.dist-info/METADATA
augment_auto-0.1.0.dist-info/WHEEL
augment_auto-0.1.0.dist-info/top_level.txt
augment_auto-0.1.0.dist-info/RECORD
